handymatt_media/__init__.py
handymatt_media/media_generator/__init__.py
handymatt_media/media_generator/media_generator.py
handymatt_media/media_generator/media_generator_ffmpeg.py
handymatt_media/media_generator/video_spitesheet.py
handymatt_media/media_generator/lib/helpers.py
handymatt_media/media_generator/lib/stills.py
handymatt_media/metadata/__init__.py
handymatt_media/metadata/image_metadata.py
handymatt_media/metadata/video_metadata.py
handymatt_media/video_analyser/__init__.py
handymatt_media/video_analyser/video_analyser.py
handymatt_media/video_preview_grid_maker/__init__.py
handymatt_media/video_preview_grid_maker/video_preview_grid_maker.py
handymatt_media-0.4.7.dist-info/METADATA
handymatt_media-0.4.7.dist-info/WHEEL
handymatt_media-0.4.7.dist-info/RECORD
