Metadata-Version: 2.4
Name: handymatt_media
Version: 0.4.7
Summary: A collection of custom media analysis/generation libraries for my personal use.
Project-URL: Homepage, https://github.com/MattThePerson/handymatt-media
Project-URL: Changelog, https://github.com/MattThePerson/handymatt-media/blob/main/CHANGELOG.md
Author-email: Matt Stirling <stirlingmattmarkus@gmail.com>
Classifier: Operating System :: OS Independent
Classifier: Programming Language :: Python :: 3
Requires-Python: >=3.8
Requires-Dist: imagehash>=4.3.2
Requires-Dist: mutagen>=1.47.0
Requires-Dist: nudenet>=3.0.8
Requires-Dist: numpy>=1.26.4
Requires-Dist: opencv-python>=4.9.0.80
Requires-Dist: piexif>=1.1.3
Requires-Dist: pillow>=11.1.0
